dailydose/__init__.py
dailydose/__main__.py
dailydose/battleship.py
dailydose/fact.py
dailydose/hang.py
dailydose/news.py
dailydose-0.1.1.dist-info/LICENSE
dailydose-0.1.1.dist-info/METADATA
dailydose-0.1.1.dist-info/WHEEL
dailydose-0.1.1.dist-info/entry_points.txt
dailydose-0.1.1.dist-info/top_level.txt
dailydose-0.1.1.dist-info/RECORD
