Metadata-Version: 2.1
Name: dailydose
Version: 0.1.1
Summary: Boredom kills. Here's a package that gives you a daily dose of fun!
Author-email: Larry Li <zl2902@nyu.edu>, Sneheel Sarangi <ss14247@nyu.edu>, Paula Seraphim <pas580@nyu.edu>, Winston Zhang <shz231@nyu.edu>
License: GPL-3.0-only
Project-URL: Homepage, https://github.com/software-students-fall2022/python-package-exercise-project-3-team-14
Project-URL: Repository, https://github.com/software-students-fall2022/python-package-exercise-project-3-team-14.git
Project-URL: Bug Tracker, https://github.com/software-students-fall2022/python-package-exercise-project-3-team-14/issues
Keywords: dailydose
Classifier: Programming Language :: Python :: 3
Classifier: Intended Audience :: Education
Classifier: License :: OSI Approved :: GNU General Public License v3 (GPLv3)
Classifier: Operating System :: OS Independent
Requires-Python: >=3.7
License-File: LICENSE
Requires-Dist: beautifulsoup4 (==4.11.1)
Requires-Dist: english-words (==1.1.0)
Provides-Extra: dev
Requires-Dist: pytest ; extra == 'dev'
